Metadata-Version: 1.0
Name: dist-gau-bi
Version: 0.1
Summary: Gaussian distributions
Home-page: UNKNOWN
Author: jahidul39306
Author-email: UNKNOWN
License: UNKNOWN
Platform: UNKNOWN
